latextable.py
latextable-1.0.1.dist-info/LICENSE
latextable-1.0.1.dist-info/METADATA
latextable-1.0.1.dist-info/WHEEL
latextable-1.0.1.dist-info/top_level.txt
latextable-1.0.1.dist-info/RECORD
