Metadata-Version: 2.1
Name: latextable
Version: 1.0.1
Summary: An extension to the texttable library that exports tables directly to Latex.
Author-email: Joseph Early <joseph.early.ai@gmail.com>
License: MIT
Project-URL: Homepage, https://github.com/JAEarly/latextable
Keywords: table,texttable,latex
Classifier: Development Status :: 5 - Production/Stable
Classifier: License :: OSI Approved :: MIT License
Classifier: Programming Language :: Python :: 3
Requires-Python: >=3.7
License-File: LICENSE
Requires-Dist: texttable
